{
  "sw": {
    "common": {
      "refresh": "Vuta kwa kuburudisha",
      "refreshing": "Kuonyesha upya...",
      "loadingMore": "Kupakia zaidi...",
      "checking": "Kukagua...",
      "sendOtp": "Kutuma OTP.",
      "dismiss": "Kumfukuza",
      "invite": "Alika",
      "showMore": "Onyesha zaidi |Tazama zaidi",
      "play": "Kucheza",
      "pause": "Paused",
      "playing": "Kucheza",
      "paused": "Paused",
      "watch": "Kuangalia",
      "read": "Soma",
      "authors": "Mwandishi |Waandishi",
      "languages": "Lugha |Lugha",
      "clear": "Wazi",
      "cancel": "Katisha",
      "change": "Badilisha",
      "continue": "Kuendelea",
      "select": "Teua",
      "saveChanges": "Hifadhi mabadiliko |Hifadhi |Sasishi",
      "newBadge": "Mpya",
      "login": "Kuingia",
      "logout": "Kuingia",
      "signup": "Jisajili",
      "settings": "Vipimo",
      "cookiePolicy": "Sera ya kuki",
      "privacy": "Faragha",
      "contactUs": "Wasiliana nasi",
      "home": "Nyumbani",
      "facebook": "Facebook",
      "google": "Google",
      "you": "Wewe",
      "retry": "Jaribu tena",
      "send": "Tuma",
      "submit": "Wasilisha",
      "share": "Shiriki |Shiriki sasa",
      "at": "Katika",
      "untilNextTime": "Hakuna shida. Hadi wakati ujao!",
      "plzWait": "Tafadhali subiri..",
      "saving": "Kuhifadhi.. |Kusasisha..",
      "search": "Tafutiza",
      "late": "Marehemu",
      "done": "Kufanyika",
      "featureUnavailable": "Kipengele hiki kitapatikana hivi karibuni. Shukrani kwa ajili ya kuonyesha maslahi!",
      "actions": {
        "cancel": "Katisha",
        "notify": "Taarifa",
        "like": "Kama",
        "recited": "Imesomwa",
        "comment": "Maoni",
        "reply": "Jibu",
        "bookmark": "Alamisho",
        "uploading": "Inapakia..",
        "deleting": "Kufuta..",
        "requesting": "Kuomba..",
        "audienceHeader": "Momineen ambaye {action}d — Momineen ambaye {action}d hii",
        "jsShareFileTypeError": "Samahani, huwezi kushiriki faili {fileType} hapa",
        "jsUpdateAvailable": {
          "header": "Sasisha inapatikana",
          "message": "Unaona toleo lililohifadhiwa la programu. Bofya 'Rudisha' ili kusasisha na kupakia maudhui na vipengele vipya.",
          "cta": "Onesha upya"
        },
        "jsImgUploaded": "Picha imepakiwa kwa mafanikio!",
        "jsImgUploadErr": "Upakiaji wa picha umeshindwa. Tafadhali jaribu tena baadaye.",
        "jsLoadingDelay": "Inachukua muda mrefu kuliko ilivyotarajiwa. Tafadhali subiri wakati tunashughulikia ombi hili."
      },
      "close": "Funga",
      "yes": "Ndiyo",
      "no": "La",
      "idk": "Sijui",
      "unknown": "Isiyojulikana",
      "completed!": "Kukamilisha!",
      "pushPrompt": {
        "heading": "Endelea hadi tarehe",
        "desc": "Kama unavyoona? Kamwe usikose sasisho na uendelee kuarifiwa kuhusu kila kitu kinachotokea karibu na arifa.<br />Je, tunaweza kukutumia arifa?",
        "cancelCta": "Niulize baadaye",
        "okCta": "Uhakika!",
        "jsPushUnsupported": "Push si mkono kwenye kifaa hiki. Unaweza kukosa arifa!"
      }
    },
    "errors": {
      "service": {
        "unavailable": "Huduma haipatikani kwa wakati huu. Tafadhali jaribu tena baadaye.",
        "unknown": "Kosa lisilojulikana lilitokea. Tafadhali jaribu tena baadaye.",
        "general": "Kosa lilitokea wakati wa kuchakata ombi lako. Tafadhali jaribu tena baadaye."
      },
      "content": {
        "unavailable": "Haikuweza kupakia yaliyomo kwa wakati huu. Tafadhali jaribu tena kwa muda.",
        "itemDetailUnavailable": "Haikuweza kupata maelezo ya {item} hii",
        "loadMoreError": "Imeshindwa kupakia vipengee zaidi. Tafadhali jaribu tena baadaye."
      },
      "url": {
        "invalid": "URL batili. Tafadhali jaribu URL mpya."
      },
      "page404": {
        "title": "Ukurasa haupatikani",
        "desc": "Hatukuweza kupata ukurasa unaotafuta!",
        "ctaLabel": "Nyumba ya Goto"
      }
    },
    "navbar": {
      "home": {
        "title": "Nyumbani"
      },
      "postDetail": {
        "commonTitle": "Undani",
        "fatihaTitle": "Surah-fatiha",
        "fatihaWithNamaz": "Surah-fatiha & Namaz-e-Wahshat",
        "avatarUpdateTitle": "Picha ya wasifu",
        "bannerUpdateTitle": "Picha ya jalada (Imefafanuliwa)",
        "statusUpdateTitle": "Sasisho la hali"
      }
    },
    "tabs": {
      "home": {
        "name": "Nyumbani",
        "postDetail": {
          "shareRequest": {
            "header": "Shiriki ombi hili kwenye mtandao wako na uwafikie watu zaidi!"
          }
        }
      },
      "media": {
        "name": "Midia",
        "boxLabels": {
          "nauhe": "Nauhe",
          "majalis": "Majalis",
          "soaz": "Soazi",
          "ziyarat": "Ziyaraat",
          "dua": "Mbili",
          "munajat": "Munajaat",
          "munajaat": "Munajaat",
          "books": "Vitabu"
        },
        "inviteFriends": "Waalike marafiki zako",
        "notShia": "Sio ya Shia?",
        "contacts": {
          "accessRequestHeader": "Ufikiaji wa Anwani unahitajika",
          "accessRequestDesc": "Tunahitaji ufikiaji wa anwani zako ili kupendekeza watu wa Shia kwenye kitabu chako cha simu kualika kwenye programu hii."
        },
        "audio": "Sikizi",
        "video": "Video",
        "hijri": "Hijri",
        "duaHome": {
          "wishCtaText": "Nakutakia marafiki zako!",
          "wishCtaLabel": "UNATAKA"
        },
        "books": {
          "booksByAuthor": "Vitabu vya {author}",
          "booksInLang": "Vitabu vya {lang}",
          "filterBy": "Kichujio kwa:",
          "matching": {
            "authors": "na waandishi wanaolingana",
            "lang": "na lugha zinazolingana",
            "title": "na vinavyolingana kwa kichwa"
          }
        },
        "booksFilter": {
          "title": "Pata kitabu kwa mwandishi",
          "searchBox": "Tafuta mwandishi kwa jina",
          "selectLang": "Chagua lugha:"
        },
        "bookDetails": {
          "title": "{title} - Pata vitabu zaidi vya bure kama hivi kwenye Bazm",
          "aboutBook": "Kuhusu kitabu:"
        }
      },
      "tools": {
        "name": "Zana",
        "salatAlarmDesc": "Weka kengele kwa Azaan kulingana na nyakati zako za karibu",
        "sehriAlarmDesc": "Weka Kengele kwa Sehri, au hata pata simu ya kuamka kwenye nambari yako kabla ya Sehri!",
        "sehriAlarmOptionDisabled": "Alarms kwa Sheri wakati wa mwezi wa Ramadhani (inapatikana tu wakati wa Ramadhani)",
        "tasbeehCounterDesc": "Soma Duas, Quran na Tasbeeh kwenye hali ya kurudia kwa urahisi na Audio Tasbeeh counter",
        "qnaLabel": "QnA (Masle-Masayel)",
        "qnaDesc": "Tafuta na Uliza maswali au pata majibu ya masle-masayel kutoka kwa maisha yako ya kila siku juu ya masuala ya Uislamu.",
        "khumsLabel": "Kikokotoo Cha Khums",
        "khumsDesc": "Kokotoa khums zako, au ongeza khums yoyote iliyolipwa hapo awali. Inakusaidia kuweka rekodi ya khums zako kwa miaka.",
        "alarms": {
          "salatAlarms": "Kengele za Salat - - Kengele za Salat za Kila Siku",
          "sehriAlarms": "Kengele ya Ramadhani Sehri",
          "gettingLocation": "Kupata mahali pako. Tafadhali subiri...",
          "settingsTip": "Badilisha <b>Mahali</b> na mapendeleo katika mipangilio ya Kengele. Bofya ikoni ya Mipangilio ili kuanza.",
          "setAlarmHeader": "Weka Kengele za Kila Siku",
          "setAlarmOnAppDesc": "Kwenye Eneo-kazi, arifa ya kengele huonekana tu kama bendera bila pete yoyote",
          "imsakLabel": "Imsak",
          "fajrLabel": "Fajr",
          "sunsetLabel": "Sunset",
          "maghribLabel": "Maghrib",
          "midnightLabel": "Usiku wa manane",
          "sehriEndTime": "Muda wa mwisho wa Sehri",
          "minToImsak": [
            "{min} dakika kabla ya Imsak",
            "{hour} saa kabla ya Imsak"
          ],
          "minToImsakDesc": [
            "Kengele hulia dakika {min} kabla ya mwisho wa muda wa Sehri",
            "Kengele hulia saa {hour} kabla ya mwisho wa muda wa Sehri"
          ],
          "notRamadan": "Inaonekana kuwa sio Ramadhani bado. Tafadhali rudi wakati au kabla ya Ramadhani kuweka Alarms kwa Sehri",
          "push": {
            "heading": "Ufikiaji wa arifa unahitajika",
            "desc_request": "Kengele inafanya kazi kwa kutuma arifa za kushinikiza kwa nyakati zilizoteuliwa. Bila ufikiaji wa kushinikiza, programu haitafanya kazi kwa njia inayotarajiwa. Tafadhali ruhusu ufikiaji wa arifa yako ya kushinikiza ili tuweze kukujulisha wakati wa kengele.",
            "desc_denied": "<strong>Ulikataa ufikiaji wa arifa mapema.</strong> Inahitajika kwa maelezo ya kushinikiza kufanya kazi vizuri. Tunatuma arifa kwa wakati wa kengele.<br/>Kwa upole ruhusu ufikiaji wa arifa za kushinikiza kwa kubofya kitufe.",
            "cta": "Ruhusu",
            "toast_granted": "Asante! Utaarifiwa wakati wa kengele sasa.",
            "toast_denied": "Ombi la arifa limekataliwa. Tafadhali ruhusu ufikiaji wa programu kufanya kazi vizuri.",
            "toast_prompt": "Unahitaji kuruhusu ufikiaji wa arifa kuweka kengele."
          },
          "jsAlarmSetSuccess": "Kengele zilizowekwa kwa mafanikio",
          "jsAlarmSetError": "Kosa katika kuweka kengele. Tafadhali jaribu tena baadaye.",
          "jsAlarmSnoozed": "Alarm snoozed kwa dakika 10",
          "sunriseLabel": "Jua la jua",
          "dhuhrLabel": "Zuhr",
          "asrLabel": "Asr",
          "ishaLabel": "Nyumbani"
        },
        "alarmSetting": {
          "title": "Mipangilio ya Kengele",
          "locationTitle": "Tafuta mji kwa muda wa Alarm",
          "forLocation": "Kengele kwa ajili ya mahali",
          "calcMethod": "Njia ya kuhesabu",
          "selectAdhanSound": "Chagua sauti ya Adhan",
          "selectAlarmSound": "Chagua sauti ya Kengele",
          "alarmSoundDesc": "Sauti kwa nyakati zisizo za salat",
          "timesPeekHeading": "Onyesha bendera ya nyakati",
          "timesPeekDesc": "Unaweza kuzima onyesho la mwonekano wa haraka wa nyakati kwa Salat hapa:",
          "timesPeekHome": "Onyesha kwenye ukurasa wa milisho:",
          "timesPeekTools": "Onyesha kwenye ukurasa wa zana:",
          "jsConfirmLocChange": "Kubadilisha eneo lako kutaghairi kengele zote zilizowekwa hapo awali. Kuendelea?",
          "jsOtherSettingsSaved": "Mipangilio mingine imehifadhiwa. Eneo hilo halikubadilishwa."
        },
        "qna": {
          "title": "Majibu ya swali",
          "qnaSource": "Chanzo",
          "seeAnswer": "Angalia majibu",
          "noAnswer": "Hakuna jibu"
        },
        "qnaDetail": {
          "title": "Jibu: {ques}",
          "jsSubmitSuccess": "Swali lako limewasilishwa kwa mafanikio. Tutakusasisha mara tu tutakapopokea jibu juu yake."
        },
        "tasbeehCounter": {
          "title": "Tasbeeh Counter"
        },
        "khums": {
          "list": {
            "blog": {
              "title": "Blog: Kokotoa khums kwa ufanisi",
              "p1": "<a href='{href}' target='_blank'>Fuata blogu yetu</a> ambayo inaangazia vitu muhimu katika hesabu ya khums kila mwaka.",
              "p2": "Jibu: Blogu sio mwongozo. <strong>Fuata maamuzi ya Marjah yako kwa hesabu ya Khums</strong>. <span id='blog-info-link' color='primary'>Bofya hapa</span> kwa maelezo zaidi.",
              "blogInfo": "Blogu hapo juu inategemea makala kutoka kwa al-islam.org, sistani.org, na majadiliano yetu na wasomi wengine wachache. Unapaswa kufuata maamuzi ya Marjah yako kwa hesabu ya Khums.",
              "dismissCta": "Si nia ya"
            },
            "title": "Mahesabu yako ya Khums",
            "nextMuqammasHeading": "<strong>Muqammas</strong><br />kwa hesabu inayofuata",
            "muqammasDesc": "Kulingana na hesabu kutoka mwaka wa hivi karibuni",
            "sahmeSadat": "Sahm-e-Sadat",
            "sahmeImam": "Hadiyth (a.s.)",
            "paid": "Kulipwa:",
            "remaining": "Iliyobaki:",
            "newMuqammas": "Muqammas mpya:",
            "jsDeleted": "Hesabu ya Khums ilifutwa kwa mafanikio!",
            "prompts": {
              "delete": {
                "header": "Futa Hesabu ya Khums?",
                "desc": "Una uhakika unataka kufuta hii? Nyaraka zote zinazohusiana zitafutwa pia!"
              }
            },
            "empty": {
              "header": "Hakuna khums iliyoongezwa bado",
              "subtext": "Anza kwa kuongeza hesabu ya khums. Bonyeza kwenye kitufe hapa chini."
            }
          },
          "detail": {
            "title": "Khums yako",
            "header": "Khums",
            "mqmsInfo": "Muqammas kwa hesabu inayofuata",
            "calcHeader": "Kulingana na hesabu hapa chini:",
            "savingsHeader": "Akiba",
            "conversionInfo": "Imebadilishwa kuwa {amount} kulingana na kiwango cha ubadilishaji wa {xchgRate} kwenye {xchgRateDate}",
            "expensesHeader": "Gharama",
            "mqmsHeader": "Muqammas",
            "prevMqms": "Muqammas ya awali",
            "paymentsHeader": "Malipo yaliyofanywa kwa khums:",
            "error": {
              "header": "Oh, makosa yalitokea!",
              "desc": "Inaonekana kama hatuwezi kupata chochote kuhusu hesabu hii ya khums. Inaweza kuwa kwa sababu moja ya huduma zetu zimeharibika, au labda unatafuta data ya stale.<br /><br/ >Jaribu kuburudisha ukurasa, au tufikie ikiwa unafikiria kuna kosa kwa upande wetu."
            },
            "js": {
              "recordDeleteFailed": "Kosa lilitokea wakati wa kujaribu kufuta rekodi hii. Tafadhali jaribu tena, au ikiwa kosa litaendelea, rudi tena baadaye.",
              "recordDeleted": "Rekodi imefutwa kwa mafanikio",
              "deleteRecordHeader": "Futa rekodi?",
              "deleteRecordDesc": "Una uhakika unataka kufuta rekodi hii? Viambatisho vyovyote vilivyoongezwa kwenye rekodi hii vitafutwa pia!"
            }
          },
          "calc": {
            "subtext": "Jaza fomu hapa chini ili kuhesabu khums zako. Sehemu za hiari zinaonyeshwa. Bofya info-icon hapa chini ili kujua zaidi kuhusu sehemu hiyo.",
            "blog": "Habari Nyingine: Soma blogu yetu juu ya <a href='{href}' target='_blank'>Jinsi ya kuhesabu khums kwa<a> ufanisi</a>",
            "dateRange": "Chagua masafa ya tarehe:",
            "dateRangeInfo": "Kwa kawaida, watu huhesabu khums kwa mwaka wa fedha (kwa mfano, kutoka Aprili hadi Machi) au mwaka wa Kalenda (Jan hadi Desemba)",
            "startDate": "Tarehe ya kuanza:",
            "endDate": "Tarehe ya mwisho:",
            "savings": {
              "header": "Akiba",
              "desc": "Ongeza akiba/usawa katika akaunti yako",
              "info": "Unaweza kuongeza kiasi katika sarafu tofauti, lakini khums hatimaye huhesabiwa kwa sarafu moja kulingana na kiwango cha ubadilishaji wa leo.",
              "form": {
                "label": "Lebo",
                "placeholder": "Kwa mfano, akaunti ya mshahara",
                "amountLabel": "Kiasi",
                "amountPlaceholder": "Ingiza Kiasi",
                "remarks": "Maoni yoyote kuhusu bidhaa hii?"
              }
            },
            "expenses": {
              "header": "<strong>Deni / Uwezo / Gharama</strong> - Hiari",
              "subtext": "Ongeza madeni yoyote ya haraka, madeni au gharama",
              "info": "Baadhi ya kiasi kutoka usawa inaweza kukatwa kwa khums. Fuata kiungo chetu hapo juu <strong>Kokotoa khums kwa ufanisi</strong> ili kujua zaidi.",
              "form": {
                "placeholder": "Kwa mfano, kodi ya kodi"
              }
            },
            "mqms": {
              "header": "<strong>Muqammas ya awali</strong> — Hiari",
              "subtext": "Mizani kushoto baada ya kulipa khums katika kipindi cha awali",
              "info": "Ikiwa unalipa khums kwa mara ya kwanza, Muqammas itakuwa ZERO. Ikiwa umehifadhi mahesabu ya awali hapa, unaweza kusawazisha kutumia Muqammas kutoka kipindi cha awali."
            },
            "mainCurrencyHeader": "Chagua sarafu kuu",
            "mainCurrencyInfo": "Ni sarafu gani tunapaswa kutumia kuhesabu khums?",
            "customRates": {
              "header": "<strong>Kutumia viwango vya ubadilishaji</strong>",
              "subtext": "Viwango hivi vya ubadilishaji wa sarafu vitatumika kwa hesabu. Unaweza kuzibadilisha ili kutumia maadili ya kawaida.",
              "info": "Wakati wa kushughulika na data ya kihistoria, kama vile wakati wa kuongeza hesabu kwa khums kutoka zaidi ya mwaka mmoja uliopita wakati viwango vya ubadilishaji havikuwa sawa na leo, unaweza kuweka maadili ya desturi kwa viwango vya ubadilishaji mwenyewe.",
              "rateValuePH": "Katika {currency}, kwa mfano, 1 {mainCurrency} = 80.21 {currency}"
            },
            "calculateCta": "Kokotoa",
            "pageError": {
              "header": "Kosa limetokea",
              "desc": "Imeshindwa kupata data inayohitajika kwa ukurasa. Tafadhali pakia tena ukurasa au jaribu tena baadaye."
            },
            "js": {
              "remarks": {
                "deleteHeader": "Futa maoni?",
                "deleteText": "Una uhakika unataka kufuta maoni kwa kipengee hiki?"
              },
              "choicePrompt": {
                "addHeader": "Ongeza",
                "savings": "Ongeza ingizo jipya kwenye Akiba",
                "liability": "Ongeza ingizo jipya kwa Dhima"
              },
              "rowOptions": {
                "header": "Unataka kufanya nini na hii?",
                "duplicate": "Unda ingizo la nakala",
                "remarks": "Ongeza maoni kwa hili",
                "delete": "Futa ingizo hili"
              },
              "apiError": "Kosa limetokea. Tafadhali jaribu tena."
            }
          }
        }
      },
      "user": {
        "name": "Mtumiaji |Akaunti",
        "editProfile": "Hariri Wasifu",
        "publishToFeed": "Chapisha mabadiliko yangu kwa kulisha",
        "shareUpdateToFeed": "Pia shiriki sasisho hili kwa malisho yangu",
        "statusText_ph": "Tumia _italics_ au *bold* uumbizaji kupamba hali yako",
        "statusCharsLeft": "{count} wahusika kushoto",
        "jsImgUploadSuccess": "Picha zilizopakiwa kwa mafanikio!",
        "unauthAccess": {
          "heading": "Una uhakika kuwa uko katika nafasi sahihi?",
          "desc": "<p>Inaonekana kama ulikuwa unajaribu kufikia ukurasa ambao haukuwa na ruhusa. Ikiwa ulikuwa unajaribu kufikia ukurasa ambao umefikia hapo awali, jaribu kuingia; Hii inapaswa kutatua tatizo.</p><p>Tafadhali jisikie huru kuwasiliana nasi ikiwa tatizo litaendelea.</p>"
        },
        "guest": {
          "welcome": "Karibu, <strong>Mgeni!</strong>",
          "heading": "Kwa nini kuingia au kujiandikisha?",
          "desc": "Ukiwa na akaunti kwenye programu yetu, unaweza kutumia huduma kadhaa. Anza kwa kufungua akaunti, ikiwa huna akaunti tayari. Au, kuingia tu!",
          "unlockHeading": "Fungua zifuatazo kwa akaunti:",
          "features": {
            "engage": {
              "heading": "Shiriki kwenye programu",
              "desc": "Shiriki na watumiaji wengine, jibu kwa machapisho yao au maombi, maoni maoni yako, weka alama kwenye vitu vyako, na mengi zaidi!"
            },
            "fatiha": {
              "heading": "Maombi ya Fatiha",
              "desc": "Tuma ombi kwa Surah-e-Fatiha kwa roho za wapendwa wako walioondoka na kuzibariki roho zao kwa maombi ya watumiaji wetu wote!"
            },
            "askQues": {
              "heading": "Uliza Maswali",
              "desc": "Uliza maswali kutoka kwa Deen & Duniya juu ya mada mbalimbali ili kujibiwa na eminence yake, Ayatullah Al-Sayyid Ali Al-Husseini Al-Sistani!"
            },
            "content": {
              "heading": "Maudhui yanayopendelewa",
              "desc": "Daima angalia maudhui na mipangilio unayopendelea wakati umeingia kwenye akaunti yako. Pia, kupata taarifa kwa ajili ya mambo yote ya kuvutia!"
            },
            "personalized": {
              "heading": "Kushiriki kwa kibinafsi",
              "desc": "Weka maudhui ya kushiriki yaliyobinafsishwa na saini yako ili marafiki wako wajue unaposhiriki ujumbe/chapisho."
            }
          }
        },
        "about": {
          "title": "Kuhusu",
          "jsStatusUpdateFail": "Imeshindwa kusasisha hali. Tafadhali jaribu tena baadaye.",
          "statusTextInfo": "Ongeza kitu kifupi juu yako mwenyewe, kama vile, wewe ni nani au unafanya nini!",
          "statusCta": "Ongeza Hali |Hali ya Sasisha",
          "addCity": "Ongeza Mji",
          "gender": "Mwanaume — — Mwanamke",
          "addGender": "Ongeza Jinsia",
          "addBday": "Ongeza Siku ya Kuzaliwa",
          "addRelation": "Ongeza Uhusiano",
          "privateInfoDesc": "Habari hii inaonekana kwako tu na unaona maudhui na vipengele kulingana na hii.",
          "idSetupCta": "Sanidi utambulisho wako",
          "idVerifyCta": "Thibitisha",
          "joinDate": "Kujiunga na: {date}"
        },
        "posts": {
          "title": "Posts",
          "userNoPosts": "Unapobadilisha picha yako / picha ya kufunika, au unapoomba surah-fatiha kwa wapendwa wako walioharibika, machapisho haya yataonekana hapa na kwenye kichupo cha <b>Nyumbani</b> (ya wengine pia). Jaribu kuongeza picha au picha ya jalada?",
          "profileNoPosts": "{name} hajatoa machapisho yoyote mpaka sasa."
        },
        "marhumeen": {
          "title": "Marhumeen",
          "header": {
            "marhumeenNotAdded": "{name} hajaongeza marhumeen bado — Hujaongeza marhumeen bado",
            "marhumeenAdded": "{name} ameongeza kufuatia marhumeen — Umeongeza zifuatazo marhumeen"
          },
          "jsDeleteHeader": "Una uhakika?",
          "jsDeletePrompt": "Kufuta rekodi za <b>{fullName}</b> pia itafuta maombi yote ya awali yaliyotolewa kwa {gender}! Kuendelea?",
          "jsDeleted": "Rekodi zilizofutwa kwa {marhumeen}"
        },
        "verifyCard": {
          "title": "Thibitisha utambulisho wako wa Shia -- Thibitisha utambulisho wako wa Sadat",
          "p1": "Umeonyesha katika wasifu wako kwamba wewe ni Muislamu wa Shia. Kuwa na habari hii kuthibitishwa kutawezesha vipengele zaidi kwako na kutusaidia kujenga jamii iliyothibitishwa ya Waislamu wa Shia.",
          "p2": "Kwa fadhili thibitisha utambulisho wako; Haitachukua muda mrefu",
          "noReminder": "Usinikumbushe tena",
          "dismissCta": "Sio sasa",
          "startCta": "Kuanza"
        },
        "verifyPrompt": {
          "jsGetVerified": "Unahitaji kuthibitishwa kwanza kabla ya kuthibitisha wengine!",
          "jsLinkExpired": "Kiungo hiki ni batili au kimeisha muda wake. Tafadhali wasiliana na rafiki yako ili utoe ombi jipya.",
          "confirm": {
            "heading": "Thibitisha Utambulisho wa Akaunti",
            "msg": "Msaada {firstName} kupata taarifa {genderLabel1} akaunti kuthibitishwa. Hii itawawezesha {genderLabel2} kufikia vipengele zaidi kwenye programu yetu",
            "jsSkip": "Hakuna shida. Ukibadilisha mawazo yako, unaweza kupitia tena kiungo hiki ili kuthibitisha baadaye."
          }
        },
        "myKhums": {
          "title": "Khums yangu"
        }
      }
    },
    "sidemenu": {
      "left": {
        "accountLogin": "Ingia kwenye akaunti yako",
        "createAccount": "Unda akaunti"
      }
    },
    "comps": {
      "common": {
        "nextStep": "Hatua inayofuata",
        "goBack": "Rudi",
        "confirm": "Thibitisha"
      },
      "timesBanner": {
        "errors": {
          "locUnavailable": "Mahali hapapatikani. Tafadhali weka kwa kubofya ikoni ili kuona mwonekano wa haraka wa nyakati za Salat.",
          "unknownError": "Kosa limetokea. Haikuweza kupakia nyakati kwa wakati huu."
        }
      },
      "langPrompt": {
        "title": "Tumia programu katika {langLabel}?",
        "desc": {
          "p1": "Inaonekana kama unapata programu kutoka {countryName}. Je, ungependa kuona maudhui na udhibiti katika mojawapo ya lugha zifuatazo zinazozungumzwa katika eneo hilo? Bonyeza kwenye chaguo lako na kisha bofya 'Hifadhi' kuendelea.",
          "p2": "Au, ondoa ibukizi hii ili kuendelea kutumia programu kwa lugha chaguo-msingi."
        },
        "choices": {
          "useLang": [
            "Ndiyo, tumia {langName}",
            "Tumia {langName}"
          ],
          "useEnglish": "Endelea kwa Kiingereza",
          "selectFrom": "Au, chagua kutoka kwa mojawapo ya lugha mbadala zifuatazo:"
        },
        "langError": "Kosa lilitokea wakati wa kupakia tafsiri za {langName}. Tafadhali jaribu tena baadaye."
      },
      "createPost": {
        "heading": "Ni nini leo kuhusu?",
        "desc": "Bonyeza hapa kushiriki sasisho au kutumia chaguo kutoka chini",
        "request": "Ombi",
        "askQues": "Uliza Swali",
        "sheetOptions": {
          "header": "Fanya ombi",
          "subheader": "Fanya ombi kutoka kwa momineen kwa marhumeen yako au wewe mwenyewe.",
          "requestFatiha": "Surah-fatiha/Namaz-e-Wahshat",
          "sehatDua": "Mbili-e-Afya *",
          "requestZiyarat": "Ziyarat katika Zari-e-Imam Husain (a.s.) kwa niaba yako"
        },
        "modal": {
          "titles": {
            "post": "Unda Chapisho |Sasisha Chapisho",
            "livestream": "Mto wa moja kwa moja",
            "hadiyah": "Unda Hadiyah |Sasisha Hadiyah"
          },
          "postCta": "Chapisho -- — Sasisha",
          "stream": {
            "scheduleCta": "Hifadhi kwa baadaye -- Anza Utiririshaji"
          },
          "hadiya": {
            "dedication": {
              "placeholder": "Unataka kutoa zawadi hii kwa nani?",
              "addPeopleToggle": "Wacha wengine wawe sehemu ya hii sawab pia!",
              "searchInput": "Alika momimeen kutoka Bazm au orodha yako ya Mawasiliano",
              "minUsersHeader": "Unataka kuweka idadi ya chini ambayo washiriki wanahitaji kuchagua?",
              "minUsersInput": "Ingiza namba ya chini"
            }
          },
          "postTime": [
            "Ni wakati gani?",
            "Unataka kuanza lini ku-download?"
          ],
          "whereIsIt": "Iko wapi?",
          "findLocation": "Tafuta mahali",
          "locationSubtext": "Ongeza mahali kwenye chapisho lako",
          "addLocation": "Ongeza mahali",
          "addPics": "Ongeza picha kwenye chapisho lako",
          "previewDes": "Hivi ndivyo chapisho lako litaonekana katika kulisha watu wengine. Watu wanaweza kugonga kwenye video ili kuiona kwenye skrini kamili.",
          "addToPost": "Ongeza kwa {postType} (hiari)",
          "jsImgUploadFail": "Picha haikupakiwa",
          "jsAddDetailToPost": "Tafadhali ongeza maelezo kwenye chapisho lako",
          "jsValidEndDate": "Tafadhali chagua tarehe halali ya mwisho",
          "jsSetLocation": "Tafadhali weka mahali kwa ajili ya chapisho",
          "jsRemLocation": "Tafadhali weka mahali au ondoa sehemu hiyo",
          "jsAddImg": "Tafadhali ongeza picha au ondoa sehemu hiyo",
          "jsInvalidDate": [
            "Tafadhali weka tarehe halali ya kuanza ",
            "Tafadhali weka tarehe halali ya kuanza au ondoa sehemu hiyo"
          ]
        }
      },
      "comments": {
        "name": "Maoni",
        "loadPrevious": "Pakia maoni ya awali |Pakia majibu ya awali",
        "replyingTo": "Kujibu kwa:",
        "noComments": "Hakuna maoni juu ya chapisho hili bado",
        "textboxPlaceholder": "Andika maoni yako hapa",
        "requestToLogin": "Ingia au Jisajili ili kuanza majadiliano"
      },
      "post": {
        "addressYou": "Wewe",
        "addressing": "yako — — yake — yake",
        "itemTypes": {
          "avatar": "Picha ya Avatar",
          "banner": "picha ya bango",
          "status": "hali ya wasifu"
        },
        "displayPhrase": {
          "common": "<strong>{username}</strong> updated {addressing} {item}",
          "fatiha": [
            "<strong>{username}</strong> aliomba Surah-Fatiha kwa {addressing} {relation}",
            "<strong>{username}</strong> aliomba Surah-Fatiha & Namaz-e-Wahshat kwa {addressing} {relation}"
          ]
        },
        "dateUntil": "Hadi: {date} kwa {time}",
        "privatePost": "Chapisho hili linaonekana kwako tu",
        "descZiyaratRequest": "Uliomba Ziyarat afanywe kwa niaba yako katika *haram* ya Imam Husein (a.s.) kwenye *{date}*"
      },
      "addEditRel": {
        "title": {
          "request": "Omba Surah-al-fatiha",
          "addUpdate": [
            "Sasisha kupendwa moja",
            "Ongeza mpendwa mmoja"
          ]
        },
        "heading": [
          "Ongeza mpendwa ambaye amepita",
          "Chagua mpendwa kutoka kwenye orodha au ongeza mpendwa ambaye amepita"
        ],
        "addNew": "Ongeza Mpya",
        "subheader": [
          "Ongeza maelezo ya mpendwa wako",
          "Unaweza pia kuingiza ujumbe katika ombi lako"
        ],
        "form": {
          "jsAddImg": "Ongeza picha kwa mpendwa wako",
          "jsRemoveImg": "Ondoa taswira",
          "fullName": "Jina Kamili la Marehemu",
          "name_ph": "Kwa mfano, Syed Zeeshan Haider Abidi",
          "fathersName": "Jina la Baba (kama linapatikana)",
          "father_ph": "Kwa mfano, Syed Tauqeer Husain",
          "nameError": "Tafadhali ingiza jina kamili na wahusika wowote maalum",
          "genderLabel": "Jinsia",
          "genderValue": [
            null,
            "Kiume"
          ],
          "relation": [
            "Marhooma ni wako",
            "Marhoom ni wako"
          ],
          "selectRelation": "Chagua Uhusiano",
          "demiseLabel": "Kukataliwa leo? Omba Namaz-e-Wahshat",
          "demiseText": "Tunasikitika sana kusikia kuhusu kupoteza kwako. Mwenyezi Mungu akupe wewe na familia yako nguvu ya kuvumilia hasara hii kwa uvumilivu na Mwenyezi Mungu aipe nafsi iliyoharibika kwa nafasi za juu katika Jannah. Kuchagua chaguo hili hukuwezesha kuuliza momineen kwa Namaz-e-Wahshat kwa roho iliyoharibika.",
          "optional": "Hiari",
          "dod": "Alifariki kwenye",
          "dob": "Alizaliwa kwenye"
        },
        "relation": [
          "Binti wa",
          "Mwana wa"
        ],
        "born": "Kuzaliwa:",
        "died": "Alikufa:",
        "addMsg": "Unataka kuongeza ujumbe?",
        "addMsg_ph": "Kwa mfano:\nInna lillahi wa inna ilaihe raje'un. Tafadhali soma surah-e-fatiha na 2-rak'at namaz-e-wahshat kwa mjomba wangu, Syed Zeeshan Haider wald Syed Tauqeer Hasan Marhoom, ambaye alituacha sote tukilia nyuma kukutana na muumbaji wake.",
        "remainingChars": "Wahusika: {count} — Wahusika: {count} iliyobaki",
        "infoEditRelative": "Unaweza kuhariri maelezo ya {name} katika <b>akaunti yako > sehemu ya Marhumeen</b>",
        "saveRequestCta": [
          "Hifadhi na Omba",
          "Ombi"
        ],
        "addUpdate": "Ongeza |Sasishi",
        "jsRequesting": "Kuomba..",
        "jsAddSuccess": [
          "Ongeza mpendwa wako kwa mafanikio!",
          "Sasisha mpendwa wako kwa mafanikio!"
        ],
        "jsAddFail": "Umeshindwa kuongeza mpendwa wako. Tafadhali jaribu tena baadaye.",
        "jsReqSuccess": "Ombi lililowasilishwa kwa ufanisi.",
        "jsGettingMarhumeen": "Pata marhumeen yako"
      },
      "askQues": {
        "title": "Uliza swali",
        "form": {
          "quesLabel": "Swali lako",
          "quesLabel_ph": "Tafuta swali au jiulize mwenyewe",
          "similarQues": "Maswali haya yanaweza kuwa na jibu unalotafuta.",
          "quesTextHeader": "Swali lako:",
          "selectCat": "Weka kategoria ya Swali:",
          "askAnonLabel": "Uliza bila kujulikana?",
          "askAnonInfo": "Jina lako halitatumwa kwa Msomi wakati wa kuomba jibu kwa niaba yako, wala haitaonyeshwa kwenye programu yetu na swali hili. Lakini maswali yasiyojulikana hayawezi kujibiwa haraka.",
          "askViaLabel": "Uliza kwa njia",
          "askSistaniInfo": "Unaweza kuuliza swali la kujibiwa na ofisi ya eminence yake, Ayatullah Al-Sayyid Ali Al-Husseini Al-Sistani. Tutawasilisha swali kwenye tovuti yao (pamoja na maelezo yako ya wasifu). Hakikisha umesoma Masharti <b>na Masharti</b> vizuri.",
          "tncLabel": "Masharti na Masharti:",
          "sistaniOrgTncInfo": "Fikiria vidokezo vifuatavyo kutoka kwenye wavuti yao kabla ya kuuliza swali, kwa sababu ikiwa hufuati alama zilizo chini, huenda usisikilize kutoka kwao, au hauwezi kupokea majibu yoyote.",
          "userInfo": {
            "aboutLabel": "Kuhusu wewe",
            "genderLabel": "Jinsia yako",
            "bdayLabel": "Siku yako ya kuzaliwa",
            "bdayDesc": "Unaweza kuuliza swali tu ikiwa una umri wa miaka 09."
          },
          "jsQuesAdded": "Swali limeongezwa kwa mafanikio."
        },
        "askQuesCta": "Uliza swali lako"
      },
      "authPrompt": {
        "title": "Akaunti inahitajika",
        "defLabel": "Ingia au Jisajili ili uendelee",
        "infoText": "Kipengele hiki kinahitaji kuingia au kujiandikisha kabla ya kuitumia. Bofya <b>Ingia</b> ikiwa tayari umesajiliwa, au bofya <b>Jisajili</b> ili kuunda akaunti yako."
      },
      "location": {
        "title": "Badilisha Mahali",
        "search_ph": "Tafuta mahali pako",
        "autoDetectInfo": "Ingiza eneo lako au bofya ikoni ya kitambulishi kiotomatiki ili kupata eneo lako.",
        "setLocation": "Weka mahali",
        "ipAddress": "Anwani ya IP",
        "alarmLocation": "Mahali pa kengele",
        "basedOn": "Mahali kulingana na {selector} yako",
        "jsDetecting": "Kuchunguza, tafadhali kusubiri.",
        "jsPermDenied": "Ruhusa ya mahali imekataliwa kwa programu. Tafadhali weka upya upendeleo wa eneo la programu hii kwa kutembelea sehemu ya Mipangilio kwenye simu yako.",
        "jsPosUnavailable": "Tunasikitika, lakini nafasi haipatikani kwa simu hii sasa hivi. Tafadhali jaribu tena baadaye.",
        "jsMatchNotFound": "Sikuweza kupata maeneo yoyote yanayolingana.",
        "jsEnterValidLoc": "Tafadhali ingiza mahali halali",
        "jsGeoUnavailable": "Tunasikitika, lakini nafasi haipatikani kwa simu hii sasa hivi. Tafadhali jaribu tena baadaye.",
        "jsLocMissing": "Sikuweza kupata mahali pako. Tafadhali ingiza mahali kwa manually.",
        "jsSelectedLoc": "Kuna kosa katika eneo hili. Tafadhali jaribu tena"
      },
      "readText": {
        "ctaLabel": "Soma",
        "title": "Pili: {title}",
        "arabicCta": "Kiarabu",
        "englishCta": "Kiingereza",
        "translatedCta": "Kutafsiriwa"
      },
      "reqAccess": {
        "heading": "upatikanaji unahitajika",
        "subheading": "Tunahitaji ruhusa ya kufikia kamera yako",
        "subtext": "Tafadhali ruhusu ufikiaji kwa kubofya kitufe hapa chini:",
        "ctaLabel": "ruhusu ufikiaji"
      },
      "shareBtn": {
        "subtext": "Bofya moja ya chaguo hapa chini ili kushiriki hii kwenye programu husika:",
        "jsCopyToCB": "Imenakiliwa kwenye ubao wako wa kunakili",
        "copyText": "Bofya <b>ikoni ya Nakili</b> hapo juu ili kunakili yaliyomo hapa chini:"
      },
      "verifyMob": {
        "title": [
          "Thibitisha Simu ya Mkononi",
          "Ingiza msimbo"
        ],
        "page1": {
          "infoText1": "Tunahitaji nambari yako ya simu ili kuthibitisha utambulisho wako. Unaweza pia kupata sasisho za mara kwa mara.",
          "infoText2": [
            "Ingiza nambari yako na ubofye kitufe ili kupata msimbo wako wa uthibitisho:",
            "Ingiza nambari yako na ubofye kitufe ili kupata msimbo wako wa uthibitisho:"
          ]
        },
        "form": {
          "mobileLabel": "Nambari ya Simu ya Mkononi",
          "mobileLabel_ph": "Ingiza nambari yako ya simu",
          "otpViaSMS": "Pata kupitia SMS",
          "viaWhatsApp": "Pata kupitia WhatsApp",
          "viaTelegram": "Pata kupitia Telegram",
          "viaSignal": "Pata kupitia Ishara"
        },
        "page2": {
          "header": "Tumetuma nambari ya uthibitisho wa tarakimu 6 kwa nambari yako ({number})",
          "enterCodeLabel": "Ingiza Msimbo",
          "enterCode_ph": "Ingiza msimbo wa tarakimu 6",
          "resendCode": "Msimbo wa kutuma tena",
          "notUsingMobile": "Je, si kutumia <strong>{number}</strong>?",
          "changeNumber": "Badilisha Namba"
        },
        "jsVerifySuccess": "Simu ya mkononi imethibitishwa kwa mafanikio",
        "jsVerifyError": "Kosa limetokea. Tafadhali jaribu tena baadaye.",
        "jsSendOtpFailed": "Imeshindwa kutuma OTP. Tafadhali jaribu tena baadaye.",
        "jsSendOtpSuccess": "OTP imetumwa kwa {mobile}",
        "jsTooManyRequests": "Inaonekana kama umejaribu mara nyingi sana. Tafadhali subiri kwa dakika moja au mbili na jaribu tena."
      },
      "userSettings": {
        "personalSharingMsg": "Binafsisha ujumbe wa Kushiriki",
        "changePwd": "Badilisha nywila |Weka Nywila",
        "changeLang": "Badilisha Lugha",
        "publishToFeed": "Chapisha mabadiliko yangu kwa kulisha pia."
      },
      "userSettingsModal": {
        "title": {
          "personalize": "Ubinafsishaji",
          "changePwd": "@:comps.userSettings.changePwd",
          "setLang": "@:comps.userSettings.changeLang"
        },
        "sign": {
          "addNameToMsgs": "Ongeza jina langu kwenye ujumbe",
          "sharingDesc": "Wakati wa kushiriki nje, ujumbe wako unaweza kuonekana kama hapa chini:",
          "sharingTextDemo": [
            "Sikiliza hii Nauha kwenye App ya Bazm",
            "{name} inapendekeza kusikiliza hii Nauha kwenye Programu ya Bazm"
          ],
          "addSignDesc": "Unataka kuongeza saini yako pia?",
          "addSignPlaceholder": "Kwa mfano,\nKwa matakwa bora,\n{name}",
          "signDesc": "Unaposhiriki matakwa yako na marafiki kwenye programu hii, saini yako itaongezwa kwenye ujumbe. Kwa mfano, inaweza kuonekana kama hapa chini:"
        },
        "changePwd": {
          "currentPwdLabel": "Ingiza nywila yako iliyopo:",
          "currentPwdPH": "Ingiza Nywila ya Sasa",
          "newPwdLabel": "Ingiza nywila mpya:",
          "newPwdPH": "Ingiza Nywila Mpya"
        },
        "changeLang": {
          "searchYourLang": "Tafuta lugha yako",
          "desc": "Chagua lugha ambayo ungependa kuona maudhui ya programu. Bofya kwenye lugha na subiri (inachukua wakati mwingine kupakia tafsiri) ili kuona jinsi maneno haya yanavyoonekana katika lugha iliyochaguliwa."
        },
        "jsPwdInvalid": "Nywila ina vibambo batili.",
        "jsPwdCharCount": "Nenosiri haliwezi kuwa chini ya herufi 8.",
        "jsSelectLang": "Tafadhali chagua lugha kwanza.",
        "jsLangSet": "Lugha imetayarishwa kwa {lang}",
        "jsPrefSaved": "Mipangilio ya ubinafsishaji imehifadhiwa."
      },
      "forgotPwd": {
        "title": "Umesahau nywila?",
        "introText": "Kuweka upya nywila yako ni rahisi. Chagua njia ya kuendelea:",
        "usePhoneCta": "Tumia Simu",
        "useEmailCta": "Tumia Barua pepe",
        "sendEmailIntro": "Ingiza anwani ya barua pepe ambayo uliunda akaunti yako, na tutatuma barua pepe iliyo na kiungo ili kusanidi nenosiri jipya la akaunti yako.",
        "emailInputLabel": "Barua pepe yako iliyosajiliwa",
        "sendEmailCta": "Tuma Weka upya Barua pepe",
        "sentEmailText": "Ikiwa una akaunti na sisi, utapata barua pepe ya kuweka nenosiri muda mfupi kwenye <strong>{email}</strong>. Tafadhali angalia barua pepe yako kwa kiungo.",
        "notUsingEmailText": "Je, si kutumia <strong>{email}</strong>?",
        "changeEmailCta": "Badilisha Barua pepe",
        "phoneIntroText": "Ingiza nambari ya simu iliyoongezwa kwenye akaunti yako. Tutatuma OTP ili kuthibitisha umiliki wako, na katika hatua inayofuata, utaweza kuunda nenosiri jipya.",
        "phoneInputLabel": "Nambari yako ya rununu",
        "sendOtpCta": "Tuma OTP",
        "backToLoginCta": "Rudi kwenye Ingia",
        "disclaimerText": "Tafadhali kumbuka kuwa utapata {item} tu ikiwa una {item} iliyosajiliwa na sisi",
        "jsMailSent": "Barua iliyotumwa",
        "title2": "Madai ya akaunti yako",
        "claimIntroHeading": "Kudai akaunti yako kwa haraka!",
        "claimIntroText": "Shukrani kwa ajili ya kujiunga nasi. Tumekuwekea akaunti kwa ajili yako sasa. Pata ufikiaji wa akaunti yako kwa kuweka upya nywila yake kwa kutumia mojawapo ya njia zifuatazo:"
      },
      "resetPwd": {
        "title": "Weka upya Nywila",
        "introText": "Weka nenosiri salama kwa akaunti yako hapa. Bonyeza {icon} ili kuhakikisha kuwa unaingiza nenosiri sahihi.",
        "pwdInputLabel": "Weka nywila mpya",
        "pwdInputPH": "Ingiza nywila mpya",
        "invalidPwdChars": "Vibambo batili katika nywila",
        "jsResetSuccess": "Kuweka upya nenosiri kwa mafanikio!"
      },
      "mediaPlayer": {
        "jsTrackLoadFailed": "Imeshindwa kupakia wimbo. Tafadhali jaribu tena baadaye."
      },
      "moreBtn": {
        "jsItemDeleted": "{item} kufutwa kwa mafanikio.",
        "jsErrReporting": "Haiwezi kutoa taarifa hii kwa sasa. Tafadhali jaribu tena baadaye.",
        "jsAlreadyReported": "Tayari umeripoti {item}hii. Huwezi kutoa taarifa zaidi ya mara moja.",
        "jsPromptHeading": "Kuripoti matokeo ya bidhaa katika nafasi ya chini ya kuonekana katika malisho/kurasa zako au nyingine. Je, bado unataka kutoa taarifa hii?",
        "jsReporting": "Kuripoti {itemType}..",
        "jsReportingErr": "Haikuweza kuwasilisha ombi lako kwa wakati huu. Tafadhali jaribu tena baadaye.",
        "jsReported": "{item} taarifa. Shukrani kwa ajili ya mchango wako."
      },
      "editProfileModal": {
        "jsEmptyData": "Hakuna kitu cha kusasisha!",
        "jsProfileUpdated": "Profaili imesasishwa!"
      },
      "reqZiyarat": {
        "title": "Omba Ziyarat",
        "cta": "Ombi",
        "header": "Omba Ziyarat katika Imam Hussain (a.s.) Shrine huko Karbala kwa niaba yako.",
        "desc": {
          "p1": "Kila Ijumaa, <strong>Ziyarat amekariri kwa niaba yako</strong> katika Kaburi la Imam Hussain (a.s.) huko Karbala, Iraq! Wote unahitaji kufanya ni kufanya maombi <strong>kabla ya mwisho wa Alhamisi jioni</strong>. Wewe kamwe ni kuchelewa sana ingawa; Ikiwa ombi lako litakuja kuchelewa sana, itaandikishwa kwa wiki inayofuata.",
          "p2": "Tutakujulisha wakati ziyarat imesomwa kwa niaba yako.",
          "p3": "Kumbuka: Unapoomba kwa mara ya kwanza, maelezo yako yatashirikiwa na mtoa huduma wetu. Tafadhali soma Masharti na Masharti yetu ili kujua zaidi."
        },
        "jsRegistered": "Asante! Ombi lako limesajiliwa kwa mafanikio. Utapata barua ya uthibitisho hivi karibuni.",
        "jsAlreadyRegistered": "Tayari umejiandikisha kwa Ziyarat Alhamisi hii. Jisajili wiki ijayo kwa ziyarat ya wiki ijayo.",
        "jsConfirm": "Ili kujiandikisha kwa ombi hili, tunahitaji kushiriki maelezo yako (kwa mfano, jina kamili, jinsia, nk) na mtoa huduma wetu. Hii inahitajika kwa mara ya kwanza tu. Kwa upole thibitisha kuendelea.",
        "jsDeclined": "Sawa! Pengine baadaye."
      },
      "currencySelector": {
        "title": "Chagua sarafu",
        "baseCurrency": "Fedha ya Msingi",
        "compHasOwnRates": "Ukurasa unaotumia kiteuzi hiki una viwango vya ubadilishaji ambavyo vinaweza kuwa na maadili ya kihistoria. Kwa hivyo, viwango vilivyoonyeshwa hapa havitatumika kwenye uteuzi.",
        "cancelCta": "Katisha",
        "doneCta": "Kufanyika"
      },
      "mqmsSelector": {
        "title": "Chagua kiasi cha Muqammas",
        "dateAdded": "Imeongezwa kwenye: {date}",
        "cancelCta": "Katisha",
        "doneCta": "Teua"
      },
      "khumsPaymentRecord": {
        "title": "Ongeza Rekodi ya Malipo",
        "paymentFor": "Malipo kwa {khumsType}",
        "totalAmount": "Jumla ya Kiasi: {amount}",
        "form": {
          "amountLabel": "Kiasi",
          "amountPlaceholder": "Ingiza Kiasi",
          "amountErr": "Kiasi hakiwezi kuwa zaidi ya Khums",
          "dateLabel": "Tarehe ya uhamisho — Hiari",
          "dateInfo": "Ulipo tuma pesa",
          "remarks": "Maoni, ikiwa ni yoyote?",
          "remarksInfo": "Kwa mfano, 'Kulipwa kwa pesa taslimu'",
          "attach": "Ongeza viambatisho",
          "attachInfo": "Unaweza kuongeza risiti za malipo (picha tu) kwa kumbukumbu ya baadaye"
        }
      },
      "dialCodeSelector": {
        "title": "Chagua Nchi",
        "searchPH": "Tafuta nchi kwa jina au msimbo wa kupiga simu"
      },
      "cards": {
        "completeProfile": {
          "profile": {
            "header": "Kamilisha wasifu wako",
            "desc": "Profaili zisizokamilika zina ufikiaji mdogo wa vipengele kwenye programu yetu. Kuwa na wasifu wako updated husaidia kwa njia kadhaa. Bonyeza hapa kujua zaidi.",
            "item1": {
              "header": "Profaili kamili zinathibitishwa kwa urahisi",
              "p1": "Wakati wa kuomba uthibitishaji wa akaunti (hatua inayofuata), husaidia wengine kukuthibitisha kwa urahisi wakati wanakujua au wanaweza kuona habari zote zinazohitajika kwa uthibitisho juu yako.",
              "p2": "Maelezo mafupi yasiyokamilika huchukua muda mrefu zaidi kuthibitishwa. Hatutaki uzuiliwe kutumia vipengele kwenye programu yetu."
            },
            "item2": {
              "header": "Angalia maudhui ya haki",
              "p1": "Unaona maudhui kulingana na mazingira yako. Tunapokuwa na habari sahihi juu yako, unaona maudhui muhimu zaidi.",
              "p2": "Kwa mfano, ikiwa umesasisha eneo lako kwa usahihi, utaona machapisho kutoka kwa jirani yako kwanza."
            },
            "cta": "Kamilisha wasifu wako"
          },
          "identity": {
            "header": "Sanidi utambulisho wako",
            "desc": "Tunakaribisha kila mtu kwenye programu yetu, lakini kwa sababu baadhi ya vipengele ni muhimu (na maana) kwa Waislamu wa Shia tu, habari hii inatusaidia kukutumikia sifa sahihi. Bonyeza hapa kujua zaidi.",
            "item1": {
              "header": "Upatikanaji wa makala kwa Waislamu wa Shia",
              "p1": "Vipengele kadhaa kwenye programu yetu vimejengwa na Waislamu wa Shia. Baadhi yao ni:",
              "ul": "<li>Maombi ya Surah-fatiha na Namaz-e-Wahshat</li><li>Kikokotoo Cha Khums</li><li>Msaada wa kifedha (khums) kwa Sadat momineen</li>",
              "p2": "Ili kufikia huduma hizi, unahitaji kuthibitisha utambulisho wako (iwe sasa au, ikiwa unachagua, baadaye)"
            },
            "item2": {
              "header": "Unaweza kusaidia momineen katika mahitaji!",
              "p1": "Hata kama hutaki kuthibitishwa, kunaweza kuwa na wengine ambao wanaweza kutaka kuthibitishwa ili kupata huduma hizi.",
              "p2": "Akaunti zilizothibitishwa tu ndizo zinaweza kuthibitisha momineen kama hiyo. Uthibitishaji pia unatusaidia kujenga jamii ya Shia iliyothibitishwa."
            },
            "item3": {
              "header": "Taarifa yako daima ni ya faragha",
              "p1": "<strong>Tunaelewa hii ni habari nyeti</strong> na hatutawahi kufichua habari hii hadharani bila idhini yako, lakini inferences bado inaweza kufanywa wakati mwingine. Kwa mfano, unapoomba uthibitisho kutoka kwa momineen nyingine, watajua kuwa wewe ni Shia.",
              "p2": "Unaweza kubofya kitufe hapa chini kusoma zaidi kuhusu mchakato wetu."
            },
            "cta": "Usanidi"
          }
        },
        "idSetup": {
          "header": "Karibu kufanyika!",
          "desc": "Unaweza kuruka hatua hii ikiwa unafurahi na maadili yetu yaliyowekwa mapema kwa mipangilio yako ya faragha na mawasiliano. Hata hivyo, si vibaya kuwa na kuangalia!",
          "privacy": {
            "header": "Sanidi faragha yako",
            "p1": "Fafanua kile wengine wanaweza kuona:",
            "ul": "<li>Weka mipangilio ya mwonekano kwa machapisho yako. Inafafanua ikiwa machapisho yako yanaweza kuonekana na mtu yeyote kwenye au mbali Bazm (kwa mfano, wakati mtu anashiriki kwenye jukwaa lingine)</li><li>Weka ni nani anayeweza kuona nini wakati wanatembelea wasifu wako</li><li>Weka jinsi habari yako inavyoonekana kwa wengine</li>"
          },
          "comm": {
            "header": "Mipangilio ya mawasiliano ya usanidi",
            "p1": "Fafanua jinsi na wakati gani ungependa kuwasiliana na wewe:",
            "ul": "<li>Weka mapendeleo yako ya arifa</li><li>Jisajili au ondoa usajili kwa arifa za barua pepe</li><li>Jisajili au ondoa usajili kwa vikumbusho</li>"
          },
          "cta": "Usanidi"
        },
        "verifyLoginInfo": {
          "mobile": {
            "header": "Thibitisha simu yako ya mkononi",
            "desc": "Bofya kwenye kiungo hapa chini ili kuthibitisha nambari yako ya simu:",
            "cta": "Anza uhakiki wa simu",
            "completed": "Simu ya mkononi imethibitishwa kwa mafanikio"
          },
          "email": {
            "header": "Thibitisha barua pepe yako",
            "desc": "Bofya kwenye kiungo hapa chini ili kupata barua pepe ya uthibitishaji kwenye kikasha chako.",
            "cta": "Anza uhakiki wa simu",
            "completed": "Simu ya mkononi imethibitishwa kwa mafanikio",
            "form": {
              "inputLabel": "Barua pepe yako:",
              "ph": "Ingiza barua pepe yako",
              "cta": "Kiungo cha uthibitishaji wa barua pepe"
            },
            "sent": {
              "desc": "Barua pepe ilitumwa kwa anwani yako ya barua pepe hapa chini. Bonyeza kiungo kwenye barua pepe yako ili kuthibitisha anwani yako ya barua pepe.",
              "incorrect": "Barua pepe isiyo sahihi?",
              "change": "Badilisha"
            },
            "resendCta": "Tuma tena Barua pepe",
            "openEmailCta": "Fungua Barua pepe",
            "verified": "Barua pepe imethibitishwa kwa mafanikio!"
          }
        }
      },
      "finishSetupPrompt": {
        "heading": "Usanidi kamili wa Akaunti",
        "desc": "Fungua vipengele vya akaunti yako kwa kumaliza usanidi wa akaunti yako. Lazima ufanye hivyo mara moja tu na inasaidia kuthibitisha maelezo yako, utambulisho wako na usanidi chaguzi za faragha kwako.",
        "gotoPageCta": "Endelea Usanidi",
        "dontRemind": "Usinikumbushe tena",
        "dismissCta": "Baadaye",
        "jsConfirmSkip": {
          "header": "Endelea baadaye?",
          "msg": "Kukamilisha hatua hii kutakufungulia vipengele vingi kwenye programu, lakini unaweza kukamilisha hatua hii baadaye pia. Nenda tu kwenye kichupo cha 'Mtumiaji' na uendelee kutoka hapo.",
          "btns": {
            "confirm": "Ndio, baadaye",
            "cancel": "Fanya hivyo sasa"
          }
        }
      },
      "idSetupModal": {
        "title": "Sanidi utambulisho wako",
        "form": {
          "religion": {
            "label": "Chagua dini yako:",
            "infoText": "Baadhi ya vipengele muhimu tu kwa Waislamu ni msingi wa taarifa hii. Data hii itaonekana kwako tu; Hata hivyo, inferences bado inaweza kufanywa (kama vile, wakati wewe kutumia moja ya makala inapatikana kwa Waislamu tu)",
            "muslim": "Kiislamu",
            "nonMuslim": "Wasio wa muziki"
          },
          "sect": {
            "label": "Chagua madhehebu yako",
            "infoText": "Vipengele kama vile Ombi la <strong>Ziyarat, Ombi la msaada, hesabu ya Khums, nk</strong> zinahitaji uthibitishe utambulisho wako wa Shia. Pia, watumiaji wasiothibitishwa wana ufikiaji mdogo wa vipengele.",
            "shia": "Shia",
            "sunni": "Wasio wa Shia"
          },
          "thanksNonMuslim": "Shukrani kwa ajili ya kuonyesha nia ya kujiunga na programu yetu. Tunatarajia kupata maudhui muhimu hapa. Tafadhali onyesha heshima kwa jamii na kufuata sheria zetu.",
          "sadat": {
            "label": "Je, wewe ni Sadat?",
            "infoText": "Habari hii inatumika katika vipengele vinavyokusudiwa kwa Waislamu wa Sadat-shia. Hata hivyo, haijawahi kuonyeshwa kama ilivyo kwa mtu yeyote. Utahitaji kuthibitisha hali yako ya kusikitisha kabla ya kupata huduma hizi.",
            "sadat": "Ndiyo",
            "nonSadat": "La"
          },
          "requested": "Uthibitishaji umeombwa",
          "required": "Uthibitishaji unahitajika",
          "verifyInfo": {
            "modalCta": "Hii ni nini?",
            "p1": "Ili kupata huduma zilizokusudiwa kwa Waislamu wa Shia, unahitaji kuthibitisha utambulisho wako wa Shia.",
            "p2": "Kama wewe ni Shia-Sadat, unahitaji kuthibitisha hilo pia. Unaweza kuiunganisha katika ombi sawa la uthibitishaji; Chagua tu <strong>Sadat</strong> hapo juu."
          },
          "verifyCta": "Thibitisha",
          "skipInfo": "Unaweza kuruka uthibitishaji ikiwa hutaki kutumia vipengele vilivyotajwa. Ili kusasisha tu maelezo yako, bofya <strong>Hifadhi na Endelea</strong>",
          "thankSunni": {
            "p1": "Shukrani kwa ajili ya kuonyesha maslahi katika programu yetu. Licha ya migawanyiko hii ya kidunia, Waislamu wote ni ndugu katika imani na ni wa Ummah ule ule wa Mtume Muhammad (S.A.W.W.)",
            "p2": "Tunatarajia kupata maudhui hapa muhimu na inatusaidia kuelewana vizuri.",
            "p3": "Kwa swali lolote / wasiwasi kuhusu sera zetu au kitu chochote, unaweza kutufikia kila wakati."
          }
        },
        "cta": [
          "Hifadhi",
          "Hifadhi na Endelea"
        ]
      },
      "verifyShiaModal": {
        "title": "Thibitisha akaunti ya {name}",
        "heading": "Unaweza kujibu hapa chini habari kuhusu {firstName}? Ikiwa sivyo, basi kataa ombi hili.",
        "desc": "Wewe tu kuwa na majaribio mawili ya kuthibitisha!",
        "descP1": "Unapowasilisha fomu hii, tutalinganisha habari na kile {firstName} kilichotolewa wakati wa kuomba uthibitisho. Tafadhali zingatia kwa sababu una majaribio mawili tu ya kujaza fomu hii kwa usahihi. Ikiwa bado unashindwa, hutaweza kuthibitisha {firstName} tena katika siku zijazo.",
        "descP2": "Ikiwa hujui {firstName}basi kataa ombi hili. Tutawajulisha na kuwaomba wamfikie mtu mwingine.",
        "rejectRequestCta": "Ombi la Kukataa",
        "form": {
          "heading": "Jibu maswali yafuatayo kuhusu {firstName} na ubofye Tuma:",
          "q1": "Unajuaje {firstName}?",
          "q2": "Dini:",
          "q3": "Sect:",
          "q4": "Je, {firstName} Sadat?",
          "q5": "Kitu kingine chochote ambacho ungependa kuongeza?"
        }
      },
      "editPrefModal": {
        "title": "Mipangilio yako ya Faragha",
        "privacy": {
          "header": "Mipangilio ya faragha",
          "desc": "Weka ni nani anayeweza kuona yafuatayo kutoka kwako au kwenye akaunti yako:",
          "form": {
            "posts": "Machapisho yako",
            "status": "Sasisho zako za hali",
            "requests": "Maombi yako",
            "relationship": "Hali ya uhusiano wako",
            "birthday": "Tarehe yako ya kuzaliwa (sio mwaka)",
            "location": "Mahali pako"
          },
          "disclaimer": {
            "heading": "* Inferences bado inaweza kufanywa juu ya hii",
            "p": "Ingawa habari hii labda imefichwa kwenye wasifu wako, baadhi ya inferences bado zinaweza kufanywa. Kwa mfano, ikiwa chapisho lako linaonekana kwa mtumiaji, wanaweza kugundua kuwa unaishi karibu (kulingana na mahali chapisho hilo linaonekana kwenye malisho yao)"
          },
          "values": {
            "everyone": "Kila mmoja",
            "users": "Momineen pekee",
            "shias": "Washia wa pekee",
            "me": "Ni mimi tu"
          }
        },
        "comm": {
          "header": "Mipangilio ya Mawasiliano",
          "desc": "Weka jinsi ungependa kuwasiliana",
          "form": {
            "push": {
              "header": "Arifa za kushinikiza",
              "nearby": "Kwa machapisho kutoka kwa watumiaji wa karibu",
              "daily": "Sasisho zetu za kila siku"
            },
            "email": {
              "header": "Arifa za barua pepe",
              "weekly": "Jarida la kila wiki",
              "monthly": "Barua pepe za muhtasari wa kila mwezi"
            },
            "cta": "Sasisha"
          }
        },
        "js": {
          "changeSaved": "Mabadiliko yaliyohifadhiwa kwa mafanikio"
        }
      },
      "rejectVerifyReq": {
        "cta": "Kataa",
        "title": "Ombi la kukataa",
        "reasonLabel": "Kwa nini hutaki kuthibitisha akaunti hii?",
        "reasonPh": "Tutawajulisha {userName} na kuwaomba wamfikie mtu mwingine kwa ajili ya uthibitisho"
      },
      "haadiHome": {
        "title": "Anza majadiliano — — Majadiliano yako na Haadi",
        "item": {
          "added": "Aliongeza {date}",
          "tokensUsed": "Tokeni zilizotumiwa: {tokens}",
          "readContinue": "Soma au endelea na mjadala"
        },
        "blank": {
          "heading": "Anzisha mjadala mpya",
          "desc": "Huna mazungumzo ya awali. Anza mjadala mpya kwa kuwasilisha hoja yako hapa chini."
        },
        "introLink": "Soma zaidi kuhusu Haadi, au",
        "inputPh": "Anzisha mjadala mpya",
        "quesHelp": {
          "invalid": "Maswali yenye maneno 5 au zaidi yana maana zaidi.",
          "goodLen": "Inaonekana kama swali nzuri!",
          "excellent": "Haijawahi kuumiza kuelezea swali lako. Heshima!"
        }
      },
      "askHaadi": {
        "title": "Ask Haadi",
        "infoText": "Ili kumaliza mjadala huu na kuanza mazungumzo mapya, bofya kitufe hapa chini",
        "newChatCTA": "Mjadala Mpya",
        "inputPH": "Uliza swali",
        "empty": {
          "heading": "Sikuweza kupata mazungumzo haya",
          "p1": "Kosa lilitokea wakati wa kujaribu kupata mazungumzo haya. Tafadhali angalia URL na jaribu tena.",
          "p2": "Ikiwa hii inaendelea kutokea, wasiliana nasi kwa upole."
        },
        "jsNewChatInfo": "Huu ni mwanzo wa mazungumzo mapya na Haadi. Umechagua kuwezesha muktadha kwa Haadi wakati unajibu maswali yako. Unaweza kuzima chaguo hili kila wakati katika mipangilio, au uone hii inamaanisha nini kwako."
      },
      "aboutHaadi": {
        "title": "Kutana na Haadi, rafiki yako wa karibu na Uislamu wa Shia!",
        "desc": "Bonyeza kila moja ya muhtasari huu kusoma zaidi, au kupata zaidi kuhusu Haadi na masharti ya matumizi katika <a href= lengo{blogLink} ='_system'>blogi yetu",
        "agreement": "Ninaelewa na kukubaliana na Masharti ya Matumizi"
      }
    },
    "authPage": {
      "form": {
        "name": {
          "label": "Jina lako",
          "placeholder": "Ingiza jina lako kamili"
        },
        "email": {
          "label": "Barua pepe",
          "placeholder": [
            "Barua pepe yako iliyosajiliwa",
            "Ingiza barua pepe yako"
          ]
        },
        "password": {
          "label": "Nywila",
          "placeholder": [
            "Nywila yako",
            "Ingiza nywila"
          ]
        },
        "rememberLogin": "Kumbuka kuingia",
        "forgotPwd": "Umesahau nywila?",
        "connectUsing": "Au, unganisha kwa kutumia",
        "useSavedAccount": "Tumia akaunti zilizohifadhiwa",
        "lastLogin": "Kuingia kwa mwisho",
        "needAccount": "Unahitaji akaunti?",
        "resetPwdSuccess": "Unaweza kutumia nenosiri lako jipya kuingia sasa",
        "jsEnterFullName": "Tafadhali ingiza jina lako kamili.",
        "jsEnterValidName": "Tafadhali ingiza jina la halali.",
        "jsEnterValidEmail": [
          "Tafadhali ingiza barua pepe halali.",
          "Barua pepe ina vibambo batili. Tafadhali ingiza barua pepe halali."
        ],
        "jsSelectCountryCode": "Tafadhali chagua msimbo wa nchi yako kutoka kwenye orodha",
        "jsEnterMobile": "Tafadhali ingiza nambari yako ya simu.",
        "jsEnterValidMobile": "Tafadhali ingiza nambari halali ya simu",
        "jsEnterPwd": "Tafadhali ingiza nenosiri lako!",
        "jsEnterValidPwd": [
          "Nywila ina vibambo batili. Tafadhali ingiza nenosiri halali.",
          "Password inapaswa kuwa angalau wahusika {num} ."
        ],
        "jsAccountSuccess": "Akaunti iliyoundwa kwa mafanikio",
        "jsFbError": "Haikuweza kupata maelezo ya akaunti yako ya Facebook. Tafadhali jaribu tena.",
        "jsPromptClosedErr": "Haraka ya kuingia ilifungwa kabla ya kumaliza. Tafadhali jaribu tena."
      },
      "gotoSignup": "Ishara ya Goto",
      "alreadyHasAccount": "Tayari una akaunti?",
      "gotoLogin": "Kuingia kwa Goto",
      "gotoProfile": "Profaili ya Goto",
      "msgForAuthUser": "<p>Tunadhani umetua hapa kwa makosa, kwani tayari umeingia.</p><p>Unaweza kuangalia profile yako kuona jinsi inaonekana, au kutumia moja ya viungo hapa chini kuvinjari sehemu nyingine:</p>",
      "jsLoggedOut": "Umeondolewa.",
      "jsLogoutHeading": "Ingia kutoka kwa akaunti?",
      "jsLogoutText": "Hii itafuta habari iliyohifadhiwa ndani ya nchi ambayo inawezesha kuingia <b>haraka</b>. Kuendelea?"
    },
    "banners": {
      "appInstall": {
        "card": {
          "heading": "Sakinisha Bazm { platform }",
          "desc": "Pakua programu yetu ya Android kwa uzoefu bora, maudhui ya kibinafsi, arifa na kila kitu cha maslahi yako kutoka karibu nawe! |Sakinisha njia ya mkato ya programu (bookmark) ili kuifikia moja kwa moja kutoka kwenye skrini yako ya nyumbani wakati ujao kwa uzoefu bora! Haichukui nafasi yoyote kwenye kifaa chako lakini inakusaidia kurudi kwenye programu haraka.",
          "cta": {
            "action": "Kusakinisha",
            "skip": "Pengine baadaye"
          }
        },
        "prompt": {
          "heading": "Sakinisha njia ya mkato ya Bazm?"
        },
        "popover": {
          "text": "Bofya kwenye ikoni ya Shiriki (inaonekana kama moja iliyo upande wa kulia) <strong>CHINI</strong> na kisha ubofye <strong>Ongeza kwenye Skrini ya Kwanza</strong>. Bofya \"Hifadhi\" ili kumaliza, na kisha unaweza kufikia programu kutoka kwa njia ya mkato kwenye skrini yako ya nyumbani!"
        },
        "nonSafari": {
          "heading": "Bazm inafanya kazi vizuri kwenye Apple Safari",
          "desc": "Kivinjari hiki kina vipengele vichache, wakati kivinjari cha Safari kinawezesha programu yetu kufanya vizuri zaidi, pamoja na maelezo ya Push na Programu-fupi.",
          "subtext": "<strong>Fungua programu ya Safari</strong> kwenye simu yako na uende <strong>{url}</strong> kwa uzoefu bora.",
          "skipCta": "Endelea hapa badala ya"
        }
      },
      "webFeedback": {
        "heading": "Ni kwa jinsi gani uzoefu wako hadi sasa?",
        "text": "<p>Unapenda app mpya? Je, kuna kitu tunaweza kuboresha? Tafadhali tusaidie na maoni yako ili kuboresha uzoefu wako!</p><p>Hii itachukua dakika chache tu, na tunathamini sana wakati wako!</p>",
        "cta": "Toa maoni",
        "dismiss": "Pengine baadaye"
      },
      "advertise": {
        "heading": "Kutangaza juu ya Bazm",
        "text": "<p>Kufikia mamilioni ya Waislamu wa Shia duniani kote na bidhaa yako kwenye Bazm au kushiriki na bidhaa na watumiaji.</p><p>Anza kwa chini kama $ 1 / siku!</p>",
        "cta": "Jifunze zaidi"
      },
      "upgradeSafari": {
        "header": "Uzoefu mdogo juu ya Safari",
        "description": "<strong>Kivinjari hiki (Safari) hakijaboreshwa kwa uzoefu bora</strong>. Kwa kuendelea kutumia programu yetu hapa, utakosa huduma kadhaa kama arifa za tahadhari, karibu na sasisho, hali ya nje ya mtandao na mengi zaidi.<br/>Tunapendekeza kupata moja ya vivinjari vilivyoorodheshwa hapa chini kwa uzoefu ulioboreshwa. Bofya vifungo vyovyote ili kupakua kivinjari kutoka AppStore:",
        "ctas": {
          "getGoogle": "Pata Google Chrome",
          "getFirefox": "Kupata Firefox ya Mozilla",
          "getOpera": "Pata Mguso wa Opera",
          "skip": "Pengine baadaye"
        },
        "toast": "Hakuna shida. Hadi wakati ujao!"
      },
      "cookieBanner": {
        "header": "Kuhusu kuhifadhi vidakuzi kwenye kifaa chako",
        "p1": "Hatuhifadhi vidakuzi vyovyote kwenye {device} yako lakini programu za wahusika wengine zinazotumiwa katika programu yetu zinaweza (kama vile, Google Analytics). Badala yake tunatumia hifadhi ya kudumu kuhifadhi data yoyote muhimu, na katika hali nyingi, hii imesimbwa kwa njia fiche katika uhifadhi na wakati wa uhamisho.",
        "p2": "Kwa kuendelea kutumia programu hii, unathibitisha kuwa huna maswala yoyote na chaguo zetu. Ili kujua zaidi kuhusu kuki zetu na matumizi ya data, angalia <a href='https://bazm.in/privacy-policy' target='_blank'>Sera yetu ya Faragha.</a>"
      }
    },
    "meta": {
      "titleBranding": " __ Bazm - App ya Mtandao wa Jamii kwa Waislamu wa Shia duniani kote! Download app hii leo.",
      "home": {
        "title": "Bazm - App ya jamii ya Shia mtandaoni!",
        "description": "Programu ya Bazm ni programu ya jamii ya Shia inayokidhi mahitaji yako yote ya kila siku ya deen & mazhab. Pata Nauhe, Majalis, Dua, Aamaal, Ziyarat, Vitabu, n.k. kwa tarehe na matukio yote. Tazama na ufanye matukio ya mkondo wa moja kwa moja na majalis na Shia-muslims duniani kote kutoka kwa urahisi wa nyumba yako. Jiunge na leo!"
      },
      "feed": {
        "title": "Pata maudhui yaliyolengwa na ushiriki na jamii ya shia karibu na wewe na ulimwengu",
        "description": "Pata na ushiriki habari, matukio, na maudhui na shia momineen karibu, na uwajulishe kuhusu matukio yoyote unayokaribisha. Jifunze kuhusu chochote kinachotokea karibu na wewe kwenye programu."
      },
      "mediaHome": {
        "title": "Bazm - Nauhe, Majalis, Dua, Ziyarat, Aamaal na mengi zaidi kwa ajili yenu!",
        "description": "Pata Nauhe, Majalis, Dua, Aamaal, ziyarat na mengi zaidi kwa tarehe na hafla zote. Tazama na ufanye majalis ya mkondo wa moja kwa moja kutoka kwa urahisi wa nyumba yako! Jiunge na programu ya mtandao wa kijamii wa Shia ambayo inakusaidia na kazi za kawaida za deen & mazhab. Jiunge na leo!"
      },
      "toolsHome": {
        "title": "Bazm - Kengele ya kila siku ya Azaan, majibu ya maswali na zana kwa Waislamu wa Shia",
        "description": "Pata ukumbusho wa kila siku kwa Adhan, pata na uulize swali-jibu juu ya mada ya deen & islam, au omba Surah-fatiha au Namaz-e-Wahshat kwa marhumeen yako, na zana zaidi kwenye Bazm. Jiunge na programu ya mtandao wa kijamii wa Shia ambayo inakusaidia na kazi za kawaida za deen. Pata Nohe/Nauhe, Majalis, Dua, Aamaal, Ziyarat kwa tarehe na hafla zote. Matukio ya mtiririko wa moja kwa moja na majalis kutoka kwa urahisi wa nyumba yako. Jiunge na leo!"
      },
      "tasbeehCounter": {
        "title": "Moja kwa moja tasbeeh counter na Sauti __ Tasbeeh Counter chombo",
        "description": "Kusoma tasbeeh isitoshe sasa ni rahisi na kaunta zetu za Sauti za tasbeeh. Soma tasbeeh yako wakati unaendesha gari au unafanya kazi, bado unafuatilia hesabu na kaunta za sauti. Pata zana hii na zingine kama hiyo kwenye programu ya Bazm. Pakua leo."
      },
      "accountHome": {
        "title": "Bazm - Unda akaunti yako ya bure leo na upate msaada na mahitaji yako ya kila siku ya deen!",
        "description": "Jiunge na programu ya Bazm leo ili kukidhi mahitaji yako yote ya deeniyat. Pata nohe/nauhe, majalis, dua, ziyarat, aamaal kwa tarehe na hafla zote. Mtiririko wa moja kwa moja na uangalie majalis na matukio kutoka karibu nawe; pata machapisho, yaliyomo na momineen kutoka kwako na ulimwenguni, na mengi zaidi kwenye programu. Jiunge leo!"
      },
      "nauheListPage": {
        "title": "Sikiliza Nauhe kutoka kwa nauhakhwan maarufu duniani kote",
        "description": "Sikiliza nauhe kutoka miaka yote na nauhakhwan zote maarufu kutoka ulimwenguni kote kwenye programu ya Bazm. Pakua leo."
      },
      "soazListPage": {
        "title": "Sikiliza Soaz kutoka Soazkhwan maarufu duniani kote",
        "description": "Sikiliza Soaz kutoka miaka yote na Soazkhwan maarufu kutoka ulimwenguni kote kwenye programu ya Bazm. Pakua leo."
      },
      "majalisList": {
        "title": "{type} majalis/majlis kwenye Bazm - Pata nauhe zaidi, sauti / video majalis, dua, ziyarat, aamaal, nk. kwenye Bazm",
        "description": "Pata sauti / video majalis kutoka Maulana na Zakir-e-Ahlbayt kutoka karibu na wewe na duniani kote. Sikiliza na uangalie vipindi vya hivi karibuni vya majalis na livestream kwenye programu ya Bazm. Pakua programu hii leo na ujiunge na mamilioni ya Waislamu wa Kishia ulimwenguni kote!"
      },
      "duasPage": {
        "title": [
          "Duas na aamaal kwa mwezi wa {month} kwenye Bazm - Pata nauhe zaidi, sauti / video majalis, dua, ziyarat, aamaal, nk. kwenye Bazm",
          "Duas na aamaal kwa miezi yote kwenye Bazm - Pata nauhe zaidi, sauti / video majalis, dua, ziyarat, aamaal, nk. kwenye Bazm"
        ],
        "description": "Pata duas, aamaal, ziyarat na munajat kwa miezi yote kwenye Bazm, tarehe na tukio la busara. Pakua programu hii leo na ujiunge na mamilioni ya Waislamu wa Kishia ulimwenguni kote!"
      }
    }
  }
}